LICENSE
README.md
pyproject.toml
onshnap/__init__.py
onshnap/cli.py
onshnap/client.py
onshnap/core.py
onshnap/py.typed
onshnap/utils.py
onshnap.egg-info/PKG-INFO
onshnap.egg-info/SOURCES.txt
onshnap.egg-info/dependency_links.txt
onshnap.egg-info/entry_points.txt
onshnap.egg-info/requires.txt
onshnap.egg-info/top_level.txt
tests/test_dummy.py