Metadata-Version: 2.4
Name: onshnap
Version: 0.1.0
Summary: Frozen-snapshot URDF/MJCF exporter for Onshape assemblies
Author-email: Wesley Maa <wesley.maa@gmail.com>
License: MIT
Project-URL: Repository, https://github.com/WT-MM/onshnap
Requires-Python: >=3.10
License-File: LICENSE
Requires-Dist: requests>=2.28.0
Requires-Dist: numpy>=1.21.0
Requires-Dist: scipy>=1.7.0
Requires-Dist: colorlogging
Provides-Extra: dev
Requires-Dist: ruff; extra == "dev"
Requires-Dist: mypy; extra == "dev"
Requires-Dist: pytest; extra == "dev"
Requires-Dist: types-requests; extra == "dev"
Dynamic: license-file
